pydiceroller/args.py
pydiceroller/pydiceroller.py
pydiceroller-0.1.1.dist-info/LICENSE
pydiceroller-0.1.1.dist-info/METADATA
pydiceroller-0.1.1.dist-info/WHEEL
pydiceroller-0.1.1.dist-info/entry_points.txt
pydiceroller-0.1.1.dist-info/top_level.txt
pydiceroller-0.1.1.dist-info/RECORD
